[{"title":"30秒飞阅雄安新区看新颜","category":"社会  ","description":"自2017年4月1日宣布设立至今，2000多个日夜，做规划、拉框架、显雏形……六岁雄安渐展新颜，“未来之城”拔节生长！","url":"https://m.weibo.cn/search?containerid=100103type%3D1%26t%3D10%26q%3D%2330%E7%A7%92%E9%A3%9E%E9%98%85%E9%9B%84%E5%AE%89%E6%96%B0%E5%8C%BA%E7%9C%8B%E6%96%B0%E9%A2%9C%23&stream_entry_id=51&isnewpage=1&extparam=seat%3D1%26filter_type%3Drealtimehot%26dgr%3D0%26pos%3D0%26cate%3D10103%26stream_entry_id%3D51%26c_type%3D51%26display_time%3D1680203044%26pre_seqid%3D1680203044773027221141&luicode=10000011&lfid=106003type%3D25%26t%3D3%26disable_hot%3D1%26filter_type%3Drealtimehot","ads":false},{"title":"上海海事大学被举报弄虚作假","category":"社会  ","description":"上海海事大学被举报弄虚作假：教授教学成果被跨专业使用。","url":"https://m.weibo.cn/search?containerid=100103type%3D1%26t%3D10%26q%3D%23%E4%B8%8A%E6%B5%B7%E6%B5%B7%E4%BA%8B%E5%A4%A7%E5%AD%A6%E8%A2%AB%E4%B8%BE%E6%8A%A5%E5%BC%84%E8%99%9A%E4%BD%9C%E5%81%87%23&stream_entry_id=31&isnewpage=1&extparam=seat%3D1%26flag%3D0%26stream_entry_id%3D31%26q%3D%2523%25E4%25B8%258A%25E6%25B5%25B7%25E6%25B5%25B7%25E4%25BA%258B%25E5%25A4%25A7%25E5%25AD%25A6%25E8%25A2%25AB%25E4%25B8%25BE%25E6%258A%25A5%25E5%25BC%2584%25E8%2599%259A%25E4%25BD%259C%25E5%2581%2587%2523%26filter_type%3Drealtimehot%26band_rank%3D1%26realpos%3D1%26c_type%3D31%26dgr%3D0%26pos%3D0%26cate%3D5001%26lcate%3D5001%26display_time%3D1680203044%26pre_seqid%3D1680203044773027221141&luicode=10000011&lfid=106003type%3D25%26t%3D3%26disable_hot%3D1%26filter_type%3Drealtimehot","hot":143550,"ads":false},{"title":"吴磊吻戏从脸红到耳朵","category":"电视剧  ","description":"吴磊《爱情而已》吻戏从脸红到耳朵","url":"https://m.weibo.cn/search?containerid=100103type%3D1%26t%3D10%26q%3D%23%E5%90%B4%E7%A3%8A%E5%90%BB%E6%88%8F%E4%BB%8E%E8%84%B8%E7%BA%A2%E5%88%B0%E8%80%B3%E6%9C%B5%23&stream_entry_id=31&isnewpage=1&extparam=seat%3D1%26flag%3D16%26stream_entry_id%3D31%26q%3D%2523%25E5%2590%25B4%25E7%25A3%258A%25E5%2590%25BB%25E6%2588%258F%25E4%25BB%258E%25E8%2584%25B8%25E7%25BA%25A2%25E5%2588%25B0%25E8%2580%25B3%25E6%259C%25B5%2523%26filter_type%3Drealtimehot%26band_rank%3D2%26realpos%3D2%26c_type%3D31%26dgr%3D0%26pos%3D1%26cate%3D5001%26lcate%3D5001%26display_time%3D1680203044%26pre_seqid%3D1680203044773027221141&luicode=10000011&lfid=106003type%3D25%26t%3D3%26disable_hot%3D1%26filter_type%3Drealtimehot","hot":"剧集 140417","ads":false},{"title":"这里的春景每一帧都是画报","category":"社会  ","description":"浙江杭州太子湾公园春色醉人，山障水绕、曲径通幽，郁金香五彩缤纷，樱花如云似雪，处处相映成景。","url":"https://m.weibo.cn/search?containerid=100103type%3D1%26t%3D10%26q%3D%23%E8%BF%99%E9%87%8C%E7%9A%84%E6%98%A5%E6%99%AF%E6%AF%8F%E4%B8%80%E5%B8%A7%E9%83%BD%E6%98%AF%E7%94%BB%E6%8A%A5%23&stream_entry_id=31&isnewpage=1&extparam=seat%3D1%26flag%3D0%26stream_entry_id%3D31%26q%3D%2523%25E8%25BF%2599%25E9%2587%258C%25E7%259A%2584%25E6%2598%25A5%25E6%2599%25AF%25E6%25AF%258F%25E4%25B8%2580%25E5%25B8%25A7%25E9%2583%25BD%25E6%2598%25AF%25E7%2594%25BB%25E6%258A%25A5%2523%26filter_type%3Drealtimehot%26band_rank%3D3%26realpos%3D3%26c_type%3D31%26dgr%3D0%26pos%3D2%26cate%3D5001%26lcate%3D5001%26display_time%3D1680203044%26pre_seqid%3D1680203044773027221141&luicode=10000011&lfid=106003type%3D25%26t%3D3%26disable_hot%3D1%26filter_type%3Drealtimehot","hot":96592,"ads":false},{"title":"魅族20好看好用","category":"\n                \n                                            \n                        魅族科技\n                                    \n                            ","url":"https://m.weibo.cn/search?containerid=100103type%3D1%26t%3D10%26q%3D%23%E9%AD%85%E6%97%8F20%E5%A5%BD%E7%9C%8B%E5%A5%BD%E7%94%A8%23&stream_entry_id=31&isnewpage=1&extparam=seat%3D1%26lcate%3D5001%26band_rank%3D4%26pos%3D3%26topic_ad%3D1%26q%3D%2523%25E9%25AD%2585%25E6%2597%258F20%25E5%25A5%25BD%25E7%259C%258B%25E5%25A5%25BD%25E7%2594%25A8%2523%26dgr%3D0%26stream_entry_id%3D31%26cate%3D5001%26c_type%3D31%26adid%3D184837%26filter_type%3Drealtimehot%26display_time%3D1680203044%26pre_seqid%3D1680203044773027221141&luicode=10000011&lfid=106003type%3D25%26t%3D3%26disable_hot%3D1%26filter_type%3Drealtimehot","hot":"","ads":true},{"title":"林更新说和赵丽颖二搭更默契了","category":"电视剧-国产剧  ","description":"林更新说和赵丽颖二搭《与凤行》更默契了","url":"https://m.weibo.cn/search?containerid=100103type%3D1%26t%3D10%26q%3D%23%E6%9E%97%E6%9B%B4%E6%96%B0%E8%AF%B4%E5%92%8C%E8%B5%B5%E4%B8%BD%E9%A2%96%E4%BA%8C%E6%90%AD%E6%9B%B4%E9%BB%98%E5%A5%91%E4%BA%86%23&stream_entry_id=31&isnewpage=1&extparam=seat%3D1%26flag%3D0%26stream_entry_id%3D31%26q%3D%2523%25E6%259E%2597%25E6%259B%25B4%25E6%2596%25B0%25E8%25AF%25B4%25E5%2592%258C%25E8%25B5%25B5%25E4%25B8%25BD%25E9%25A2%2596%25E4%25BA%258C%25E6%2590%25AD%25E6%259B%25B4%25E9%25BB%2598%25E5%25A5%2591%25E4%25BA%2586%2523%26filter_type%3Drealtimehot%26band_rank%3D4%26realpos%3D4%26c_type%3D31%26dgr%3D0%26pos%3D4%26cate%3D5001%26lcate%3D5001%26display_time%3D1680203044%26pre_seqid%3D1680203044773027221141&luicode=10000011&lfid=106003type%3D25%26t%3D3%26disable_hot%3D1%26filter_type%3Drealtimehot","hot":"剧集 82963","ads":false},{"title":"官方通报林场主求水事件","category":"社会  ","description":"灵武市委、市政府按照自治区党委、政府关于地方党委政府要主动担当的要求，对国家能源集团宁夏煤业公司双马一矿与孙某供水纠纷所涉新种和拟种苗木，已经采取有效保护措施。","url":"https://m.weibo.cn/search?containerid=100103type%3D1%26t%3D10%26q%3D%23%E5%AE%98%E6%96%B9%E9%80%9A%E6%8A%A5%E6%9E%97%E5%9C%BA%E4%B8%BB%E6%B1%82%E6%B0%B4%E4%BA%8B%E4%BB%B6%23&stream_entry_id=31&isnewpage=1&extparam=seat%3D1%26flag%3D0%26stream_entry_id%3D31%26q%3D%2523%25E5%25AE%2598%25E6%2596%25B9%25E9%2580%259A%25E6%258A%25A5%25E6%259E%2597%25E5%259C%25BA%25E4%25B8%25BB%25E6%25B1%2582%25E6%25B0%25B4%25E4%25BA%258B%25E4%25BB%25B6%2523%26filter_type%3Drealtimehot%26band_rank%3D5%26realpos%3D5%26c_type%3D31%26dgr%3D0%26pos%3D5%26cate%3D5001%26lcate%3D5001%26display_time%3D1680203044%26pre_seqid%3D1680203044773027221141&luicode=10000011&lfid=106003type%3D25%26t%3D3%26disable_hot%3D1%26filter_type%3Drealtimehot","hot":79326,"ads":false},{"title":"全球男性精子量告急","category":"社会  ","description":"此前数据显示，全球男性精子数量呈持续下降状态。北京儿童医院顺义妇儿医院泌尿外科医生莫志强介绍，有研究显示，近50年以来，男性精子数量下降幅度超过60%，降低一半以上。这一研究表明，威胁人类社会的不只是老龄化，还有精子质和量的持续下降。","url":"https://m.weibo.cn/search?containerid=100103type%3D1%26t%3D10%26q%3D%23%E5%85%A8%E7%90%83%E7%94%B7%E6%80%A7%E7%B2%BE%E5%AD%90%E9%87%8F%E5%91%8A%E6%80%A5%23&stream_entry_id=31&isnewpage=1&extparam=seat%3D1%26flag%3D0%26stream_entry_id%3D31%26q%3D%2523%25E5%2585%25A8%25E7%2590%2583%25E7%2594%25B7%25E6%2580%25A7%25E7%25B2%25BE%25E5%25AD%2590%25E9%2587%258F%25E5%2591%258A%25E6%2580%25A5%2523%26filter_type%3Drealtimehot%26band_rank%3D6%26realpos%3D6%26c_type%3D31%26dgr%3D0%26pos%3D6%26cate%3D5001%26lcate%3D5001%26display_time%3D1680203044%26pre_seqid%3D1680203044773027221141&luicode=10000011&lfid=106003type%3D25%26t%3D3%26disable_hot%3D1%26filter_type%3Drealtimehot","hot":64230,"ads":false},{"title":"交个朋友千万福利送不停","category":"电商  ","description":"交个朋友三周年庆典，罗永浩淘宝直播间，千万福利送不停，更有免单锦鲤等，快来看看吧！","url":"https://m.weibo.cn/search?containerid=100103type%3D1%26t%3D10%26q%3D%23%E4%BA%A4%E4%B8%AA%E6%9C%8B%E5%8F%8B%E5%8D%83%E4%B8%87%E7%A6%8F%E5%88%A9%E9%80%81%E4%B8%8D%E5%81%9C%23&stream_entry_id=31&isnewpage=1&extparam=seat%3D1%26lcate%3D5001%26band_rank%3D7%26pos%3D7%26topic_ad%3D1%26q%3D%2523%25E4%25BA%25A4%25E4%25B8%25AA%25E6%259C%258B%25E5%258F%258B%25E5%258D%2583%25E4%25B8%2587%25E7%25A6%258F%25E5%2588%25A9%25E9%2580%2581%25E4%25B8%258D%25E5%2581%259C%2523%26dgr%3D0%26stream_entry_id%3D31%26cate%3D5001%26c_type%3D31%26adid%3D184716%26filter_type%3Drealtimehot%26display_time%3D1680203044%26pre_seqid%3D1680203044773027221141&luicode=10000011&lfid=106003type%3D25%26t%3D3%26disable_hot%3D1%26filter_type%3Drealtimehot","hot":"","ads":true},{"title":"内娱小白花天花板","category":"明星-内地  ","description":"内娱顶级小白花，没人能抗拒吧！！","url":"https://m.weibo.cn/search?containerid=100103type%3D1%26t%3D10%26q%3D%23%E5%86%85%E5%A8%B1%E5%B0%8F%E7%99%BD%E8%8A%B1%E5%A4%A9%E8%8A%B1%E6%9D%BF%23&stream_entry_id=31&isnewpage=1&extparam=seat%3D1%26flag%3D0%26stream_entry_id%3D31%26q%3D%2523%25E5%2586%2585%25E5%25A8%25B1%25E5%25B0%258F%25E7%2599%25BD%25E8%258A%25B1%25E5%25A4%25A9%25E8%258A%25B1%25E6%259D%25BF%2523%26filter_type%3Drealtimehot%26band_rank%3D7%26realpos%3D7%26c_type%3D31%26dgr%3D0%26pos%3D8%26cate%3D5001%26lcate%3D5001%26display_time%3D1680203044%26pre_seqid%3D1680203044773027221141&luicode=10000011&lfid=106003type%3D25%26t%3D3%26disable_hot%3D1%26filter_type%3Drealtimehot","hot":51978,"ads":false},{"title":"这熊猫介绍真是没瞎写","category":"搞笑  ","description":"形容得太准确了","url":"https://m.weibo.cn/search?containerid=100103type%3D1%26t%3D10%26q%3D%23%E8%BF%99%E7%86%8A%E7%8C%AB%E4%BB%8B%E7%BB%8D%E7%9C%9F%E6%98%AF%E6%B2%A1%E7%9E%8E%E5%86%99%23&stream_entry_id=31&isnewpage=1&extparam=seat%3D1%26flag%3D0%26stream_entry_id%3D31%26q%3D%2523%25E8%25BF%2599%25E7%2586%258A%25E7%258C%25AB%25E4%25BB%258B%25E7%25BB%258D%25E7%259C%259F%25E6%2598%25AF%25E6%25B2%25A1%25E7%259E%258E%25E5%2586%2599%2523%26filter_type%3Drealtimehot%26band_rank%3D8%26realpos%3D8%26c_type%3D31%26dgr%3D0%26pos%3D9%26cate%3D5001%26lcate%3D5001%26display_time%3D1680203044%26pre_seqid%3D1680203044773027221141&luicode=10000011&lfid=106003type%3D25%26t%3D3%26disable_hot%3D1%26filter_type%3Drealtimehot","hot":47345,"ads":false},{"title":"那我长大了还管谁叫爷爷","category":"情感  ","description":"瞬间就破防了。","url":"https://m.weibo.cn/search?containerid=100103type%3D1%26t%3D10%26q%3D%23%E9%82%A3%E6%88%91%E9%95%BF%E5%A4%A7%E4%BA%86%E8%BF%98%E7%AE%A1%E8%B0%81%E5%8F%AB%E7%88%B7%E7%88%B7%23&stream_entry_id=31&isnewpage=1&extparam=seat%3D1%26flag%3D0%26stream_entry_id%3D31%26q%3D%2523%25E9%2582%25A3%25E6%2588%2591%25E9%2595%25BF%25E5%25A4%25A7%25E4%25BA%2586%25E8%25BF%2598%25E7%25AE%25A1%25E8%25B0%2581%25E5%258F%25AB%25E7%2588%25B7%25E7%2588%25B7%2523%26filter_type%3Drealtimehot%26band_rank%3D9%26realpos%3D9%26c_type%3D31%26dgr%3D0%26pos%3D10%26cate%3D5001%26lcate%3D5001%26display_time%3D1680203044%26pre_seqid%3D1680203044773027221141&luicode=10000011&lfid=106003type%3D25%26t%3D3%26disable_hot%3D1%26filter_type%3Drealtimehot","hot":46236,"ads":false},{"title":"海南启动全岛封关运作准备","category":"社会  ","description":"3月29日，“蓬勃兴起正当时——海南全面深化改革开放五年来进展成效”首场新闻发布会上提到，海南全面启动全岛封关运作准备。","url":"https://m.weibo.cn/search?containerid=100103type%3D1%26t%3D10%26q%3D%23%E6%B5%B7%E5%8D%97%E5%90%AF%E5%8A%A8%E5%85%A8%E5%B2%9B%E5%B0%81%E5%85%B3%E8%BF%90%E4%BD%9C%E5%87%86%E5%A4%87%23&stream_entry_id=31&isnewpage=1&extparam=seat%3D1%26flag%3D0%26stream_entry_id%3D31%26q%3D%2523%25E6%25B5%25B7%25E5%258D%2597%25E5%2590%25AF%25E5%258A%25A8%25E5%2585%25A8%25E5%25B2%259B%25E5%25B0%2581%25E5%2585%25B3%25E8%25BF%2590%25E4%25BD%259C%25E5%2587%2586%25E5%25A4%2587%2523%26filter_type%3Drealtimehot%26band_rank%3D10%26realpos%3D10%26c_type%3D31%26dgr%3D0%26pos%3D11%26cate%3D5001%26lcate%3D5001%26display_time%3D1680203044%26pre_seqid%3D1680203044773027221141&luicode=10000011&lfid=106003type%3D25%26t%3D3%26disable_hot%3D1%26filter_type%3Drealtimehot","hot":43589,"ads":false},{"title":"上海大爷挤地铁骂女子是乡下猪","category":"社会  ","description":"3月30日，上海。一大爷因排队上地铁时与女乘客发生争执，大骂女子是乡下猪。","url":"https://m.weibo.cn/search?containerid=100103type%3D1%26t%3D10%26q%3D%23%E4%B8%8A%E6%B5%B7%E5%A4%A7%E7%88%B7%E6%8C%A4%E5%9C%B0%E9%93%81%E9%AA%82%E5%A5%B3%E5%AD%90%E6%98%AF%E4%B9%A1%E4%B8%8B%E7%8C%AA%23&stream_entry_id=31&isnewpage=1&extparam=seat%3D1%26flag%3D0%26stream_entry_id%3D31%26q%3D%2523%25E4%25B8%258A%25E6%25B5%25B7%25E5%25A4%25A7%25E7%2588%25B7%25E6%258C%25A4%25E5%259C%25B0%25E9%2593%2581%25E9%25AA%2582%25E5%25A5%25B3%25E5%25AD%2590%25E6%2598%25AF%25E4%25B9%25A1%25E4%25B8%258B%25E7%258C%25AA%2523%26filter_type%3Drealtimehot%26band_rank%3D11%26realpos%3D11%26c_type%3D31%26dgr%3D0%26pos%3D12%26cate%3D5001%26lcate%3D5001%26display_time%3D1680203044%26pre_seqid%3D1680203044773027221141&luicode=10000011&lfid=106003type%3D25%26t%3D3%26disable_hot%3D1%26filter_type%3Drealtimehot","hot":43419,"ads":false},{"title":"包贝尔女儿近照","category":"明星  ","description":"包贝尔女儿近照","url":"https://m.weibo.cn/search?containerid=100103type%3D1%26t%3D10%26q%3D%23%E5%8C%85%E8%B4%9D%E5%B0%94%E5%A5%B3%E5%84%BF%E8%BF%91%E7%85%A7%23&stream_entry_id=31&isnewpage=1&extparam=seat%3D1%26flag%3D2%26stream_entry_id%3D31%26q%3D%2523%25E5%258C%2585%25E8%25B4%259D%25E5%25B0%2594%25E5%25A5%25B3%25E5%2584%25BF%25E8%25BF%2591%25E7%2585%25A7%2523%26filter_type%3Drealtimehot%26band_rank%3D12%26realpos%3D12%26c_type%3D31%26dgr%3D0%26pos%3D13%26cate%3D5001%26lcate%3D5001%26display_time%3D1680203044%26pre_seqid%3D1680203044773027221141&luicode=10000011&lfid=106003type%3D25%26t%3D3%26disable_hot%3D1%26filter_type%3Drealtimehot","hot":42838,"ads":false},{"title":"谢娜问粉丝我生图很厉害吧","category":"明星  ","description":"《萌探探探案3》 录制，谢娜酒红色小洋装搭配复古高跟鞋亮相，调皮问粉丝我生图很厉害吧。","url":"https://m.weibo.cn/search?containerid=100103type%3D1%26t%3D10%26q%3D%23%E8%B0%A2%E5%A8%9C%E9%97%AE%E7%B2%89%E4%B8%9D%E6%88%91%E7%94%9F%E5%9B%BE%E5%BE%88%E5%8E%89%E5%AE%B3%E5%90%A7%23&stream_entry_id=31&isnewpage=1&extparam=seat%3D1%26flag%3D0%26stream_entry_id%3D31%26q%3D%2523%25E8%25B0%25A2%25E5%25A8%259C%25E9%2597%25AE%25E7%25B2%2589%25E4%25B8%259D%25E6%2588%2591%25E7%2594%259F%25E5%259B%25BE%25E5%25BE%2588%25E5%258E%2589%25E5%25AE%25B3%25E5%2590%25A7%2523%26filter_type%3Drealtimehot%26band_rank%3D13%26realpos%3D13%26c_type%3D31%26dgr%3D0%26pos%3D14%26cate%3D5001%26lcate%3D5001%26display_time%3D1680203044%26pre_seqid%3D1680203044773027221141&luicode=10000011&lfid=106003type%3D25%26t%3D3%26disable_hot%3D1%26filter_type%3Drealtimehot","hot":42481,"ads":false},{"title":"张艺兴看展生图","category":"明星  ","description":"张艺兴日内瓦表展看展生图！","url":"https://m.weibo.cn/search?containerid=100103type%3D1%26t%3D10%26q%3D%23%E5%BC%A0%E8%89%BA%E5%85%B4%E7%9C%8B%E5%B1%95%E7%94%9F%E5%9B%BE%23&stream_entry_id=31&isnewpage=1&extparam=seat%3D1%26flag%3D1%26stream_entry_id%3D31%26q%3D%2523%25E5%25BC%25A0%25E8%2589%25BA%25E5%2585%25B4%25E7%259C%258B%25E5%25B1%2595%25E7%2594%259F%25E5%259B%25BE%2523%26filter_type%3Drealtimehot%26band_rank%3D14%26realpos%3D14%26c_type%3D31%26dgr%3D0%26pos%3D15%26cate%3D5001%26lcate%3D5001%26display_time%3D1680203044%26pre_seqid%3D1680203044773027221141&luicode=10000011&lfid=106003type%3D25%26t%3D3%26disable_hot%3D1%26filter_type%3Drealtimehot","hot":41983,"ads":false},{"title":"网红自称确诊肝癌内容纯属虚构","category":"社会  ","description":"25岁网红博主确诊肝癌？结果是纯属虚构，你怎么看？","url":"https://m.weibo.cn/search?containerid=100103type%3D1%26t%3D10%26q%3D%23%E7%BD%91%E7%BA%A2%E8%87%AA%E7%A7%B0%E7%A1%AE%E8%AF%8A%E8%82%9D%E7%99%8C%E5%86%85%E5%AE%B9%E7%BA%AF%E5%B1%9E%E8%99%9A%E6%9E%84%23&stream_entry_id=31&isnewpage=1&extparam=seat%3D1%26flag%3D0%26stream_entry_id%3D31%26q%3D%2523%25E7%25BD%2591%25E7%25BA%25A2%25E8%2587%25AA%25E7%25A7%25B0%25E7%25A1%25AE%25E8%25AF%258A%25E8%2582%259D%25E7%2599%258C%25E5%2586%2585%25E5%25AE%25B9%25E7%25BA%25AF%25E5%25B1%259E%25E8%2599%259A%25E6%259E%2584%2523%26filter_type%3Drealtimehot%26band_rank%3D15%26realpos%3D15%26c_type%3D31%26dgr%3D0%26pos%3D16%26cate%3D5001%26lcate%3D5001%26display_time%3D1680203044%26pre_seqid%3D1680203044773027221141&luicode=10000011&lfid=106003type%3D25%26t%3D3%26disable_hot%3D1%26filter_type%3Drealtimehot","hot":41952,"ads":false},{"title":"彭小苒47秒念台词","category":"电视剧  ","description":"@彭小苒 直播还原《春闺梦里人》季曼倍速台词，47秒无卡壳流利清晰，还自带情绪，厉害了这姐 口条真好 演技也好！","url":"https://m.weibo.cn/search?containerid=100103type%3D1%26t%3D10%26q%3D%23%E5%BD%AD%E5%B0%8F%E8%8B%9247%E7%A7%92%E5%BF%B5%E5%8F%B0%E8%AF%8D%23&stream_entry_id=31&isnewpage=1&extparam=seat%3D1%26flag%3D0%26stream_entry_id%3D31%26q%3D%2523%25E5%25BD%25AD%25E5%25B0%258F%25E8%258B%259247%25E7%25A7%2592%25E5%25BF%25B5%25E5%258F%25B0%25E8%25AF%258D%2523%26filter_type%3Drealtimehot%26band_rank%3D16%26realpos%3D16%26c_type%3D31%26dgr%3D0%26pos%3D17%26cate%3D5001%26lcate%3D5001%26display_time%3D1680203044%26pre_seqid%3D1680203044773027221141&luicode=10000011&lfid=106003type%3D25%26t%3D3%26disable_hot%3D1%26filter_type%3Drealtimehot","hot":"剧集 39758","ads":false},{"title":"千万不要在泰山顶上这样拍照","category":"搞笑  ","description":"啊这这这…拍出了一种很奇怪的画风","url":"https://m.weibo.cn/search?containerid=100103type%3D1%26t%3D10%26q%3D%23%E5%8D%83%E4%B8%87%E4%B8%8D%E8%A6%81%E5%9C%A8%E6%B3%B0%E5%B1%B1%E9%A1%B6%E4%B8%8A%E8%BF%99%E6%A0%B7%E6%8B%8D%E7%85%A7%23&stream_entry_id=31&isnewpage=1&extparam=seat%3D1%26flag%3D0%26stream_entry_id%3D31%26q%3D%2523%25E5%258D%2583%25E4%25B8%2587%25E4%25B8%258D%25E8%25A6%2581%25E5%259C%25A8%25E6%25B3%25B0%25E5%25B1%25B1%25E9%25A1%25B6%25E4%25B8%258A%25E8%25BF%2599%25E6%25A0%25B7%25E6%258B%258D%25E7%2585%25A7%2523%26filter_type%3Drealtimehot%26band_rank%3D17%26realpos%3D17%26c_type%3D31%26dgr%3D0%26pos%3D18%26cate%3D5001%26lcate%3D5001%26display_time%3D1680203044%26pre_seqid%3D1680203044773027221141&luicode=10000011&lfid=106003type%3D25%26t%3D3%26disable_hot%3D1%26filter_type%3Drealtimehot","hot":38779,"ads":false},{"title":"魅族20","category":"\n                \n                                            暂无\n                                    \n                            ","url":"https://m.weibo.cn/search?containerid=100103type%3D1%26t%3D10%26q%3D%23%E9%AD%85%E6%97%8F20%23&stream_entry_id=31&isnewpage=1&extparam=seat%3D1%26flag%3D0%26stream_entry_id%3D31%26q%3D%2523%25E9%25AD%2585%25E6%2597%258F20%2523%26filter_type%3Drealtimehot%26band_rank%3D18%26realpos%3D18%26c_type%3D31%26dgr%3D0%26pos%3D19%26cate%3D5001%26lcate%3D5001%26display_time%3D1680203044%26pre_seqid%3D1680203044773027221141&luicode=10000011&lfid=106003type%3D25%26t%3D3%26disable_hot%3D1%26filter_type%3Drealtimehot","hot":38355,"ads":false},{"title":"怪异君","category":"\n                \n                                            暂无\n                                    \n                            ","url":"https://m.weibo.cn/search?containerid=100103type%3D1%26t%3D10%26q%3D%E6%80%AA%E5%BC%82%E5%90%9B&stream_entry_id=31&isnewpage=1&extparam=seat%3D1%26flag%3D0%26stream_entry_id%3D31%26q%3D%25E6%2580%25AA%25E5%25BC%2582%25E5%2590%259B%26filter_type%3Drealtimehot%26band_rank%3D19%26realpos%3D19%26c_type%3D31%26dgr%3D0%26pos%3D20%26cate%3D5001%26lcate%3D5001%26display_time%3D1680203044%26pre_seqid%3D1680203044773027221141&luicode=10000011&lfid=106003type%3D25%26t%3D3%26disable_hot%3D1%26filter_type%3Drealtimehot","hot":37814,"ads":false},{"title":"存多少钱才算有安全感","category":"情感  ","description":"你的存款有多少？存多少钱才能让你拥有安全感？","url":"https://m.weibo.cn/search?containerid=100103type%3D1%26t%3D10%26q%3D%23%E5%AD%98%E5%A4%9A%E5%B0%91%E9%92%B1%E6%89%8D%E7%AE%97%E6%9C%89%E5%AE%89%E5%85%A8%E6%84%9F%23&stream_entry_id=31&isnewpage=1&extparam=seat%3D1%26flag%3D0%26stream_entry_id%3D31%26q%3D%2523%25E5%25AD%2598%25E5%25A4%259A%25E5%25B0%2591%25E9%2592%25B1%25E6%2589%258D%25E7%25AE%2597%25E6%259C%2589%25E5%25AE%2589%25E5%2585%25A8%25E6%2584%259F%2523%26filter_type%3Drealtimehot%26band_rank%3D20%26realpos%3D20%26c_type%3D31%26dgr%3D0%26pos%3D21%26cate%3D5001%26lcate%3D5001%26display_time%3D1680203044%26pre_seqid%3D1680203044773027221141&luicode=10000011&lfid=106003type%3D25%26t%3D3%26disable_hot%3D1%26filter_type%3Drealtimehot","hot":35419,"ads":false},{"title":"村民不认可孙国友被称为治沙英雄","category":"社会  ","description":"有网友称孙国友是“治沙英雄”，但当地村民对孙国友的治沙并不认可。“他（孙国友）说自己从2003年开始种树，将荒沙地改造成现在的模样，但是林场里的沙蒿、柠条实际上都是我们小时候村里领着我们种的，孙国友还没来林场时，这里已经是成片的沙蒿。”","url":"https://m.weibo.cn/search?containerid=100103type%3D1%26t%3D10%26q%3D%23%E6%9D%91%E6%B0%91%E4%B8%8D%E8%AE%A4%E5%8F%AF%E5%AD%99%E5%9B%BD%E5%8F%8B%E8%A2%AB%E7%A7%B0%E4%B8%BA%E6%B2%BB%E6%B2%99%E8%8B%B1%E9%9B%84%23&stream_entry_id=31&isnewpage=1&extparam=seat%3D1%26flag%3D0%26stream_entry_id%3D31%26q%3D%2523%25E6%259D%2591%25E6%25B0%2591%25E4%25B8%258D%25E8%25AE%25A4%25E5%258F%25AF%25E5%25AD%2599%25E5%259B%25BD%25E5%258F%258B%25E8%25A2%25AB%25E7%25A7%25B0%25E4%25B8%25BA%25E6%25B2%25BB%25E6%25B2%2599%25E8%258B%25B1%25E9%259B%2584%2523%26filter_type%3Drealtimehot%26band_rank%3D21%26realpos%3D21%26c_type%3D31%26dgr%3D0%26pos%3D22%26cate%3D5001%26lcate%3D5001%26display_time%3D1680203044%26pre_seqid%3D1680203044773027221141&luicode=10000011&lfid=106003type%3D25%26t%3D3%26disable_hot%3D1%26filter_type%3Drealtimehot","hot":35163,"ads":false},{"title":"男子生前借亲戚534万去世后被赖账","category":"社会  ","description":"近日，浙江温州，永嘉县法院审理一起债务纠纷。金某某2020年因交通意外死亡，家属整理遗物时发现一本笔记本，上面记录了2013年来他的款项收支，其中有多笔借钱给亲戚林某某的记录，金额达数百万元，并注明月息1分或1分2。","url":"https://m.weibo.cn/search?containerid=100103type%3D1%26t%3D10%26q%3D%23%E7%94%B7%E5%AD%90%E7%94%9F%E5%89%8D%E5%80%9F%E4%BA%B2%E6%88%9A534%E4%B8%87%E5%8E%BB%E4%B8%96%E5%90%8E%E8%A2%AB%E8%B5%96%E8%B4%A6%23&stream_entry_id=31&isnewpage=1&extparam=seat%3D1%26flag%3D0%26stream_entry_id%3D31%26q%3D%2523%25E7%2594%25B7%25E5%25AD%2590%25E7%2594%259F%25E5%2589%258D%25E5%2580%259F%25E4%25BA%25B2%25E6%2588%259A534%25E4%25B8%2587%25E5%258E%25BB%25E4%25B8%2596%25E5%2590%258E%25E8%25A2%25AB%25E8%25B5%2596%25E8%25B4%25A6%2523%26filter_type%3Drealtimehot%26band_rank%3D22%26realpos%3D22%26c_type%3D31%26dgr%3D0%26pos%3D23%26cate%3D5001%26lcate%3D5001%26display_time%3D1680203044%26pre_seqid%3D1680203044773027221141&luicode=10000011&lfid=106003type%3D25%26t%3D3%26disable_hot%3D1%26filter_type%3Drealtimehot","hot":35113,"ads":false},{"title":"SEVENTEEN将4月24日回归","category":"\n                \n                                            暂无\n                                    \n                            ","url":"https://m.weibo.cn/search?containerid=100103type%3D1%26t%3D10%26q%3D%23SEVENTEEN%E5%B0%864%E6%9C%8824%E6%97%A5%E5%9B%9E%E5%BD%92%23&stream_entry_id=31&isnewpage=1&extparam=seat%3D1%26flag%3D0%26stream_entry_id%3D31%26q%3D%2523SEVENTEEN%25E5%25B0%25864%25E6%259C%258824%25E6%2597%25A5%25E5%259B%259E%25E5%25BD%2592%2523%26filter_type%3Drealtimehot%26band_rank%3D23%26realpos%3D23%26c_type%3D31%26dgr%3D0%26pos%3D24%26cate%3D5001%26lcate%3D5001%26display_time%3D1680203044%26pre_seqid%3D1680203044773027221141&luicode=10000011&lfid=106003type%3D25%26t%3D3%26disable_hot%3D1%26filter_type%3Drealtimehot","hot":"音乐 34449","ads":false},{"title":"导演李玉刚首部电影开机","category":"明星-内地  ","description":"有谁会不相信我们的李玉刚呢？这一次适应导演的新身份，处女作《云上的云》终于开机了，主创团队都是一些非常优秀的演员，相信以李玉刚的水平一定会让我们看到一个宏大的东方美。","url":"https://m.weibo.cn/search?containerid=100103type%3D1%26t%3D10%26q%3D%23%E5%AF%BC%E6%BC%94%E6%9D%8E%E7%8E%89%E5%88%9A%E9%A6%96%E9%83%A8%E7%94%B5%E5%BD%B1%E5%BC%80%E6%9C%BA%23&stream_entry_id=31&isnewpage=1&extparam=seat%3D1%26flag%3D0%26stream_entry_id%3D31%26q%3D%2523%25E5%25AF%25BC%25E6%25BC%2594%25E6%259D%258E%25E7%258E%2589%25E5%2588%259A%25E9%25A6%2596%25E9%2583%25A8%25E7%2594%25B5%25E5%25BD%25B1%25E5%25BC%2580%25E6%259C%25BA%2523%26filter_type%3Drealtimehot%26band_rank%3D24%26realpos%3D24%26c_type%3D31%26dgr%3D0%26pos%3D25%26cate%3D5001%26lcate%3D5001%26display_time%3D1680203044%26pre_seqid%3D1680203044773027221141&luicode=10000011&lfid=106003type%3D25%26t%3D3%26disable_hot%3D1%26filter_type%3Drealtimehot","hot":"电影 33273","ads":false},{"title":"华晨宇演唱会舞台","category":"\n                \n                                            暂无\n                                    \n                            ","url":"https://m.weibo.cn/search?containerid=100103type%3D1%26t%3D10%26q%3D%23%E5%8D%8E%E6%99%A8%E5%AE%87%E6%BC%94%E5%94%B1%E4%BC%9A%E8%88%9E%E5%8F%B0%23&stream_entry_id=31&isnewpage=1&extparam=seat%3D1%26flag%3D0%26stream_entry_id%3D31%26q%3D%2523%25E5%258D%258E%25E6%2599%25A8%25E5%25AE%2587%25E6%25BC%2594%25E5%2594%25B1%25E4%25BC%259A%25E8%2588%259E%25E5%258F%25B0%2523%26filter_type%3Drealtimehot%26band_rank%3D25%26realpos%3D25%26c_type%3D31%26dgr%3D0%26pos%3D26%26cate%3D5001%26lcate%3D5001%26display_time%3D1680203044%26pre_seqid%3D1680203044773027221141&luicode=10000011&lfid=106003type%3D25%26t%3D3%26disable_hot%3D1%26filter_type%3Drealtimehot","hot":"音乐 30181","ads":false},{"title":"王嘉尔油管订阅数华人歌手第一","category":"明星-内地  ","description":"@王嘉尔 油管订阅人数突破510万，位列华人歌手第一位。","url":"https://m.weibo.cn/search?containerid=100103type%3D1%26t%3D10%26q%3D%23%E7%8E%8B%E5%98%89%E5%B0%94%E6%B2%B9%E7%AE%A1%E8%AE%A2%E9%98%85%E6%95%B0%E5%8D%8E%E4%BA%BA%E6%AD%8C%E6%89%8B%E7%AC%AC%E4%B8%80%23&stream_entry_id=31&isnewpage=1&extparam=seat%3D1%26flag%3D0%26stream_entry_id%3D31%26q%3D%2523%25E7%258E%258B%25E5%2598%2589%25E5%25B0%2594%25E6%25B2%25B9%25E7%25AE%25A1%25E8%25AE%25A2%25E9%2598%2585%25E6%2595%25B0%25E5%258D%258E%25E4%25BA%25BA%25E6%25AD%258C%25E6%2589%258B%25E7%25AC%25AC%25E4%25B8%2580%2523%26filter_type%3Drealtimehot%26band_rank%3D26%26realpos%3D26%26c_type%3D31%26dgr%3D0%26pos%3D27%26cate%3D5001%26lcate%3D5001%26display_time%3D1680203044%26pre_seqid%3D1680203044773027221141&luicode=10000011&lfid=106003type%3D25%26t%3D3%26disable_hot%3D1%26filter_type%3Drealtimehot","hot":29999,"ads":false},{"title":"袁冰妍","category":"明星  ","description":"袁冰妍，1992年1月17日出生于上海。毕业于上海戏剧学院表演系2010级本科班。在热播剧《老九门》中饰演丫头，在《回到明朝当王爷》中饰演韩幼娘，在《将夜》中饰演莫山山，在《听雪楼》中饰演舒靖容，在《琉璃美人煞》中饰演褚璇玑，在《雷霆令》中饰演葛丹，在《祝卿好》中饰演刘泠，在《落花时节又逢君》中饰演红凝，在《倾城亦清欢》中饰演凤清欢。期待冰妍每一个角色～","url":"https://m.weibo.cn/search?containerid=100103type%3D1%26t%3D10%26q%3D%E8%A2%81%E5%86%B0%E5%A6%8D&stream_entry_id=31&isnewpage=1&extparam=seat%3D1%26flag%3D0%26stream_entry_id%3D31%26q%3D%25E8%25A2%2581%25E5%2586%25B0%25E5%25A6%258D%26filter_type%3Drealtimehot%26band_rank%3D27%26realpos%3D27%26c_type%3D31%26dgr%3D0%26pos%3D28%26cate%3D5001%26lcate%3D5001%26display_time%3D1680203044%26pre_seqid%3D1680203044773027221141&luicode=10000011&lfid=106003type%3D25%26t%3D3%26disable_hot%3D1%26filter_type%3Drealtimehot","hot":28312,"ads":false},{"title":"上海月薪一万算高吗","category":"情感  ","description":"2023年一季度平均薪酬城市分布，上海以13433均薪位列榜单第一。#上海月薪一万算高吗#，大概是个什么生活水平？","url":"https://m.weibo.cn/search?containerid=100103type%3D1%26t%3D10%26q%3D%23%E4%B8%8A%E6%B5%B7%E6%9C%88%E8%96%AA%E4%B8%80%E4%B8%87%E7%AE%97%E9%AB%98%E5%90%97%23&stream_entry_id=31&isnewpage=1&extparam=seat%3D1%26flag%3D0%26stream_entry_id%3D31%26q%3D%2523%25E4%25B8%258A%25E6%25B5%25B7%25E6%259C%2588%25E8%2596%25AA%25E4%25B8%2580%25E4%25B8%2587%25E7%25AE%2597%25E9%25AB%2598%25E5%2590%2597%2523%26filter_type%3Drealtimehot%26band_rank%3D28%26realpos%3D28%26c_type%3D31%26dgr%3D0%26pos%3D29%26cate%3D5001%26lcate%3D5001%26display_time%3D1680203044%26pre_seqid%3D1680203044773027221141&luicode=10000011&lfid=106003type%3D25%26t%3D3%26disable_hot%3D1%26filter_type%3Drealtimehot","hot":26924,"ads":false},{"title":"金奎彬16位","category":"\n                \n                                            暂无\n                                    \n                            ","url":"https://m.weibo.cn/search?containerid=100103type%3D1%26t%3D10%26q%3D%E9%87%91%E5%A5%8E%E5%BD%AC16%E4%BD%8D&stream_entry_id=31&isnewpage=1&extparam=seat%3D1%26flag%3D0%26stream_entry_id%3D31%26q%3D%25E9%2587%2591%25E5%25A5%258E%25E5%25BD%25AC16%25E4%25BD%258D%26filter_type%3Drealtimehot%26band_rank%3D29%26realpos%3D29%26c_type%3D31%26dgr%3D0%26pos%3D30%26cate%3D5001%26lcate%3D5001%26display_time%3D1680203044%26pre_seqid%3D1680203044773027221141&luicode=10000011&lfid=106003type%3D25%26t%3D3%26disable_hot%3D1%26filter_type%3Drealtimehot","hot":"综艺 26655","ads":false},{"title":"爱情而已","category":"电视剧  ","description":"凯迪拉克邀请您收看《爱情而已》，由柠萌影视出品，由吴磊、周雨彤领衔主演的都市情感剧。","url":"https://m.weibo.cn/search?containerid=100103type%3D1%26t%3D10%26q%3D%E7%88%B1%E6%83%85%E8%80%8C%E5%B7%B2&stream_entry_id=31&isnewpage=1&extparam=seat%3D1%26flag%3D0%26stream_entry_id%3D31%26q%3D%25E7%2588%25B1%25E6%2583%2585%25E8%2580%258C%25E5%25B7%25B2%26filter_type%3Drealtimehot%26band_rank%3D30%26realpos%3D30%26c_type%3D31%26dgr%3D0%26pos%3D31%26cate%3D5001%26lcate%3D5001%26display_time%3D1680203044%26pre_seqid%3D1680203044773027221141&luicode=10000011&lfid=106003type%3D25%26t%3D3%26disable_hot%3D1%26filter_type%3Drealtimehot","hot":"剧集 25741","ads":false},{"title":"带着行李箱办离职","category":"搞笑  ","description":"办完离职去旅行，这也太快乐了吧…","url":"https://m.weibo.cn/search?containerid=100103type%3D1%26t%3D10%26q%3D%23%E5%B8%A6%E7%9D%80%E8%A1%8C%E6%9D%8E%E7%AE%B1%E5%8A%9E%E7%A6%BB%E8%81%8C%23&stream_entry_id=31&isnewpage=1&extparam=seat%3D1%26flag%3D0%26stream_entry_id%3D31%26q%3D%2523%25E5%25B8%25A6%25E7%259D%2580%25E8%25A1%258C%25E6%259D%258E%25E7%25AE%25B1%25E5%258A%259E%25E7%25A6%25BB%25E8%2581%258C%2523%26filter_type%3Drealtimehot%26band_rank%3D31%26realpos%3D31%26c_type%3D31%26dgr%3D0%26pos%3D32%26cate%3D5001%26lcate%3D5001%26display_time%3D1680203044%26pre_seqid%3D1680203044773027221141&luicode=10000011&lfid=106003type%3D25%26t%3D3%26disable_hot%3D1%26filter_type%3Drealtimehot","hot":25678,"ads":false},{"title":"宋茜白宇 保你平安前传","category":"\n                \n                                            暂无\n                                    \n                            ","url":"https://m.weibo.cn/search?containerid=100103type%3D1%26t%3D10%26q%3D%E5%AE%8B%E8%8C%9C%E7%99%BD%E5%AE%87+%E4%BF%9D%E4%BD%A0%E5%B9%B3%E5%AE%89%E5%89%8D%E4%BC%A0&stream_entry_id=31&isnewpage=1&extparam=seat%3D1%26flag%3D0%26stream_entry_id%3D31%26q%3D%25E5%25AE%258B%25E8%258C%259C%25E7%2599%25BD%25E5%25AE%2587%2520%25E4%25BF%259D%25E4%25BD%25A0%25E5%25B9%25B3%25E5%25AE%2589%25E5%2589%258D%25E4%25BC%25A0%26filter_type%3Drealtimehot%26band_rank%3D32%26realpos%3D32%26c_type%3D31%26dgr%3D0%26pos%3D33%26cate%3D5001%26lcate%3D5001%26display_time%3D1680203044%26pre_seqid%3D1680203044773027221141&luicode=10000011&lfid=106003type%3D25%26t%3D3%26disable_hot%3D1%26filter_type%3Drealtimehot","hot":"电影 24591","ads":false},{"title":"治沙","category":"\n                \n                                            暂无\n                                    \n                            ","url":"https://m.weibo.cn/search?containerid=100103type%3D1%26t%3D10%26q%3D%E6%B2%BB%E6%B2%99&stream_entry_id=31&isnewpage=1&extparam=seat%3D1%26flag%3D0%26stream_entry_id%3D31%26q%3D%25E6%25B2%25BB%25E6%25B2%2599%26filter_type%3Drealtimehot%26band_rank%3D33%26realpos%3D33%26c_type%3D31%26dgr%3D0%26pos%3D34%26cate%3D5001%26lcate%3D5001%26display_time%3D1680203044%26pre_seqid%3D1680203044773027221141&luicode=10000011&lfid=106003type%3D25%26t%3D3%26disable_hot%3D1%26filter_type%3Drealtimehot","hot":23261,"ads":false},{"title":"巧珍哭着跟高加林分手","category":"电视剧  ","description":"《人生之路》巧珍：“我爱你，就只盼你好”，只换来高加林一句对不起！","url":"https://m.weibo.cn/search?containerid=100103type%3D1%26t%3D10%26q%3D%23%E5%B7%A7%E7%8F%8D%E5%93%AD%E7%9D%80%E8%B7%9F%E9%AB%98%E5%8A%A0%E6%9E%97%E5%88%86%E6%89%8B%23&stream_entry_id=31&isnewpage=1&extparam=seat%3D1%26flag%3D0%26stream_entry_id%3D31%26q%3D%2523%25E5%25B7%25A7%25E7%258F%258D%25E5%2593%25AD%25E7%259D%2580%25E8%25B7%259F%25E9%25AB%2598%25E5%258A%25A0%25E6%259E%2597%25E5%2588%2586%25E6%2589%258B%2523%26filter_type%3Drealtimehot%26band_rank%3D34%26realpos%3D34%26c_type%3D31%26dgr%3D0%26pos%3D35%26cate%3D5001%26lcate%3D5001%26display_time%3D1680203044%26pre_seqid%3D1680203044773027221141&luicode=10000011&lfid=106003type%3D25%26t%3D3%26disable_hot%3D1%26filter_type%3Drealtimehot","hot":"剧集 22916","ads":false},{"title":"杨丞琳晒与姐妹们聚会合照","category":"明星-内地  ","description":"杨丞琳晒与姐妹们聚会合照，姐妹们的相聚欢[哇]欢乐时光总是过得特别快期待下次的相聚[鮮花] ​","url":"https://m.weibo.cn/search?containerid=100103type%3D1%26t%3D10%26q%3D%23%E6%9D%A8%E4%B8%9E%E7%90%B3%E6%99%92%E4%B8%8E%E5%A7%90%E5%A6%B9%E4%BB%AC%E8%81%9A%E4%BC%9A%E5%90%88%E7%85%A7%23&stream_entry_id=31&isnewpage=1&extparam=seat%3D1%26flag%3D0%26stream_entry_id%3D31%26q%3D%2523%25E6%259D%25A8%25E4%25B8%259E%25E7%2590%25B3%25E6%2599%2592%25E4%25B8%258E%25E5%25A7%2590%25E5%25A6%25B9%25E4%25BB%25AC%25E8%2581%259A%25E4%25BC%259A%25E5%2590%2588%25E7%2585%25A7%2523%26filter_type%3Drealtimehot%26band_rank%3D35%26realpos%3D35%26c_type%3D31%26dgr%3D0%26pos%3D36%26cate%3D5001%26lcate%3D5001%26display_time%3D1680203044%26pre_seqid%3D1680203044773027221141&luicode=10000011&lfid=106003type%3D25%26t%3D3%26disable_hot%3D1%26filter_type%3Drealtimehot","hot":22858,"ads":false},{"title":"大黑皮鞋睁眼了","category":"\n                \n                                            暂无\n                                    \n                            ","url":"https://m.weibo.cn/search?containerid=100103type%3D1%26t%3D10%26q%3D%E5%A4%A7%E9%BB%91%E7%9A%AE%E9%9E%8B%E7%9D%81%E7%9C%BC%E4%BA%86&stream_entry_id=31&isnewpage=1&extparam=seat%3D1%26flag%3D0%26stream_entry_id%3D31%26q%3D%25E5%25A4%25A7%25E9%25BB%2591%25E7%259A%25AE%25E9%259E%258B%25E7%259D%2581%25E7%259C%25BC%25E4%25BA%2586%26filter_type%3Drealtimehot%26band_rank%3D36%26realpos%3D36%26c_type%3D31%26dgr%3D0%26pos%3D37%26cate%3D5001%26lcate%3D5001%26display_time%3D1680203044%26pre_seqid%3D1680203044773027221141&luicode=10000011&lfid=106003type%3D25%26t%3D3%26disable_hot%3D1%26filter_type%3Drealtimehot","hot":22718,"ads":false},{"title":"请给跪地求水林场主一个公证结果","category":"社会  ","description":"万亩林场的水源没了，年过六旬的林场主孙国友满面黄土、以头抢地，跪在沙漠里崩溃大哭。事情到底怎么回事？各方如何回应？耗尽半生积蓄的林场主盼一个公正结果。","url":"https://m.weibo.cn/search?containerid=100103type%3D1%26t%3D10%26q%3D%23%E8%AF%B7%E7%BB%99%E8%B7%AA%E5%9C%B0%E6%B1%82%E6%B0%B4%E6%9E%97%E5%9C%BA%E4%B8%BB%E4%B8%80%E4%B8%AA%E5%85%AC%E8%AF%81%E7%BB%93%E6%9E%9C%23&stream_entry_id=31&isnewpage=1&extparam=seat%3D1%26flag%3D0%26stream_entry_id%3D31%26q%3D%2523%25E8%25AF%25B7%25E7%25BB%2599%25E8%25B7%25AA%25E5%259C%25B0%25E6%25B1%2582%25E6%25B0%25B4%25E6%259E%2597%25E5%259C%25BA%25E4%25B8%25BB%25E4%25B8%2580%25E4%25B8%25AA%25E5%2585%25AC%25E8%25AF%2581%25E7%25BB%2593%25E6%259E%259C%2523%26filter_type%3Drealtimehot%26band_rank%3D37%26realpos%3D37%26c_type%3D31%26dgr%3D0%26pos%3D38%26cate%3D5001%26lcate%3D5001%26display_time%3D1680203044%26pre_seqid%3D1680203044773027221141&luicode=10000011&lfid=106003type%3D25%26t%3D3%26disable_hot%3D1%26filter_type%3Drealtimehot","hot":22606,"ads":false},{"title":"声生不息后来全场大合唱","category":"综艺  ","description":"声生不息《后来》全场大合唱~","url":"https://m.weibo.cn/search?containerid=100103type%3D1%26t%3D10%26q%3D%23%E5%A3%B0%E7%94%9F%E4%B8%8D%E6%81%AF%E5%90%8E%E6%9D%A5%E5%85%A8%E5%9C%BA%E5%A4%A7%E5%90%88%E5%94%B1%23&stream_entry_id=31&isnewpage=1&extparam=seat%3D1%26flag%3D0%26stream_entry_id%3D31%26q%3D%2523%25E5%25A3%25B0%25E7%2594%259F%25E4%25B8%258D%25E6%2581%25AF%25E5%2590%258E%25E6%259D%25A5%25E5%2585%25A8%25E5%259C%25BA%25E5%25A4%25A7%25E5%2590%2588%25E5%2594%25B1%2523%26filter_type%3Drealtimehot%26band_rank%3D38%26realpos%3D38%26c_type%3D31%26dgr%3D0%26pos%3D39%26cate%3D5001%26lcate%3D5001%26display_time%3D1680203044%26pre_seqid%3D1680203044773027221141&luicode=10000011&lfid=106003type%3D25%26t%3D3%26disable_hot%3D1%26filter_type%3Drealtimehot","hot":"综艺 22490","ads":false},{"title":"aespa新歌HoldOnTight","category":"明星  ","description":"aespa演唱的Apple原创电影《Tetris》OST 歌曲Hold On Tight释出","url":"https://m.weibo.cn/search?containerid=100103type%3D1%26t%3D10%26q%3D%23aespa%E6%96%B0%E6%AD%8CHoldOnTight%23&stream_entry_id=31&isnewpage=1&extparam=seat%3D1%26flag%3D0%26stream_entry_id%3D31%26q%3D%2523aespa%25E6%2596%25B0%25E6%25AD%258CHoldOnTight%2523%26filter_type%3Drealtimehot%26band_rank%3D39%26realpos%3D39%26c_type%3D31%26dgr%3D0%26pos%3D40%26cate%3D5001%26lcate%3D5001%26display_time%3D1680203044%26pre_seqid%3D1680203044773027221141&luicode=10000011&lfid=106003type%3D25%26t%3D3%26disable_hot%3D1%26filter_type%3Drealtimehot","hot":"音乐 22484","ads":false},{"title":"江西20岁女大学生确认自杀","category":"社会  ","description":"3月30日凌晨，赣南师范大学发布情况通报。经警方调查取证，证实寻某于3月24日18时36分许跳河自杀。","url":"https://m.weibo.cn/search?containerid=100103type%3D1%26t%3D10%26q%3D%23%E6%B1%9F%E8%A5%BF20%E5%B2%81%E5%A5%B3%E5%A4%A7%E5%AD%A6%E7%94%9F%E7%A1%AE%E8%AE%A4%E8%87%AA%E6%9D%80%23&stream_entry_id=31&isnewpage=1&extparam=seat%3D1%26flag%3D0%26stream_entry_id%3D31%26q%3D%2523%25E6%25B1%259F%25E8%25A5%25BF20%25E5%25B2%2581%25E5%25A5%25B3%25E5%25A4%25A7%25E5%25AD%25A6%25E7%2594%259F%25E7%25A1%25AE%25E8%25AE%25A4%25E8%2587%25AA%25E6%259D%2580%2523%26filter_type%3Drealtimehot%26band_rank%3D40%26realpos%3D40%26c_type%3D31%26dgr%3D0%26pos%3D41%26cate%3D5001%26lcate%3D5001%26display_time%3D1680203044%26pre_seqid%3D1680203044773027221141&luicode=10000011&lfid=106003type%3D25%26t%3D3%26disable_hot%3D1%26filter_type%3Drealtimehot","hot":22475,"ads":false},{"title":"中国切阳什姐递补获伦敦奥运金牌","category":"体育  ","description":"国际奥委会执行委员会决定重新分配2012年伦敦奥运会部分项目的比赛奖牌，中国选手切阳什姐获20公里竞走金牌，刘虹和吕秀芝则递补获得银牌和铜牌。","url":"https://m.weibo.cn/search?containerid=100103type%3D1%26t%3D10%26q%3D%23%E4%B8%AD%E5%9B%BD%E5%88%87%E9%98%B3%E4%BB%80%E5%A7%90%E9%80%92%E8%A1%A5%E8%8E%B7%E4%BC%A6%E6%95%A6%E5%A5%A5%E8%BF%90%E9%87%91%E7%89%8C%23&stream_entry_id=31&isnewpage=1&extparam=seat%3D1%26flag%3D0%26stream_entry_id%3D31%26q%3D%2523%25E4%25B8%25AD%25E5%259B%25BD%25E5%2588%2587%25E9%2598%25B3%25E4%25BB%2580%25E5%25A7%2590%25E9%2580%2592%25E8%25A1%25A5%25E8%258E%25B7%25E4%25BC%25A6%25E6%2595%25A6%25E5%25A5%25A5%25E8%25BF%2590%25E9%2587%2591%25E7%2589%258C%2523%26filter_type%3Drealtimehot%26band_rank%3D41%26realpos%3D41%26c_type%3D31%26dgr%3D0%26pos%3D42%26cate%3D5001%26lcate%3D5001%26display_time%3D1680203044%26pre_seqid%3D1680203044773027221141&luicode=10000011&lfid=106003type%3D25%26t%3D3%26disable_hot%3D1%26filter_type%3Drealtimehot","hot":22454,"ads":false},{"title":"张学友演唱会","category":"明星-内地  ","description":"张学友巡回演唱会门票，@四海票务.有意可以淘宝店铺交易。保证真票，淘宝店铺名，四海票务，唯一坚持的信任,没买票的小伙伴抓紧了！咨询方式：手机号/微信号同步联系我18607945060","url":"https://m.weibo.cn/search?containerid=100103type%3D1%26t%3D10%26q%3D%23%E5%BC%A0%E5%AD%A6%E5%8F%8B%E6%BC%94%E5%94%B1%E4%BC%9A%23&stream_entry_id=31&isnewpage=1&extparam=seat%3D1%26flag%3D0%26stream_entry_id%3D31%26q%3D%2523%25E5%25BC%25A0%25E5%25AD%25A6%25E5%258F%258B%25E6%25BC%2594%25E5%2594%25B1%25E4%25BC%259A%2523%26filter_type%3Drealtimehot%26band_rank%3D42%26realpos%3D42%26c_type%3D31%26dgr%3D0%26pos%3D43%26cate%3D5001%26lcate%3D5001%26display_time%3D1680203044%26pre_seqid%3D1680203044773027221141&luicode=10000011&lfid=106003type%3D25%26t%3D3%26disable_hot%3D1%26filter_type%3Drealtimehot","hot":"音乐 22444","ads":false},{"title":"林场主跪地求水最新进展","category":"社会  ","description":"灵武市委、市政府按照自治区党委、政府关于地方党委政府要主动担当的要求，对国家能源集团宁夏煤业公司双马一矿与孙某供水纠纷所涉新种和拟种苗木，已经采取有效保护措施。","url":"https://m.weibo.cn/search?containerid=100103type%3D1%26t%3D10%26q%3D%23%E6%9E%97%E5%9C%BA%E4%B8%BB%E8%B7%AA%E5%9C%B0%E6%B1%82%E6%B0%B4%E6%9C%80%E6%96%B0%E8%BF%9B%E5%B1%95%23&stream_entry_id=31&isnewpage=1&extparam=seat%3D1%26flag%3D0%26stream_entry_id%3D31%26q%3D%2523%25E6%259E%2597%25E5%259C%25BA%25E4%25B8%25BB%25E8%25B7%25AA%25E5%259C%25B0%25E6%25B1%2582%25E6%25B0%25B4%25E6%259C%2580%25E6%2596%25B0%25E8%25BF%259B%25E5%25B1%2595%2523%26filter_type%3Drealtimehot%26band_rank%3D43%26realpos%3D43%26c_type%3D31%26dgr%3D0%26pos%3D44%26cate%3D5001%26lcate%3D5001%26display_time%3D1680203044%26pre_seqid%3D1680203044773027221141&luicode=10000011&lfid=106003type%3D25%26t%3D3%26disable_hot%3D1%26filter_type%3Drealtimehot","hot":22431,"ads":false},{"title":"王皓说这个家没海东不行","category":"电视剧-国产剧  ","description":"这个家没有海东得散！海东不愧是路炎晨的好兄弟，一边帮他解决家里的事，一边又助攻他和归晓的爱情，晨晓结婚海东必须得坐主桌！这个家没有海东是真不行！","url":"https://m.weibo.cn/search?containerid=100103type%3D1%26t%3D10%26q%3D%23%E7%8E%8B%E7%9A%93%E8%AF%B4%E8%BF%99%E4%B8%AA%E5%AE%B6%E6%B2%A1%E6%B5%B7%E4%B8%9C%E4%B8%8D%E8%A1%8C%23&stream_entry_id=31&isnewpage=1&extparam=seat%3D1%26flag%3D0%26stream_entry_id%3D31%26q%3D%2523%25E7%258E%258B%25E7%259A%2593%25E8%25AF%25B4%25E8%25BF%2599%25E4%25B8%25AA%25E5%25AE%25B6%25E6%25B2%25A1%25E6%25B5%25B7%25E4%25B8%259C%25E4%25B8%258D%25E8%25A1%258C%2523%26filter_type%3Drealtimehot%26band_rank%3D44%26realpos%3D44%26c_type%3D31%26dgr%3D0%26pos%3D45%26cate%3D5001%26lcate%3D5001%26display_time%3D1680203044%26pre_seqid%3D1680203044773027221141&luicode=10000011&lfid=106003type%3D25%26t%3D3%26disable_hot%3D1%26filter_type%3Drealtimehot","hot":"剧集 22423","ads":false},{"title":"猫夺走了新郎的风头","category":"搞笑  ","url":"https://m.weibo.cn/search?containerid=100103type%3D1%26t%3D10%26q%3D%23%E7%8C%AB%E5%A4%BA%E8%B5%B0%E4%BA%86%E6%96%B0%E9%83%8E%E7%9A%84%E9%A3%8E%E5%A4%B4%23&stream_entry_id=31&isnewpage=1&extparam=seat%3D1%26flag%3D0%26stream_entry_id%3D31%26q%3D%2523%25E7%258C%25AB%25E5%25A4%25BA%25E8%25B5%25B0%25E4%25BA%2586%25E6%2596%25B0%25E9%2583%258E%25E7%259A%2584%25E9%25A3%258E%25E5%25A4%25B4%2523%26filter_type%3Drealtimehot%26band_rank%3D45%26realpos%3D45%26c_type%3D31%26dgr%3D0%26pos%3D46%26cate%3D5001%26lcate%3D5001%26display_time%3D1680203044%26pre_seqid%3D1680203044773027221141&luicode=10000011&lfid=106003type%3D25%26t%3D3%26disable_hot%3D1%26filter_type%3Drealtimehot","hot":22410,"ads":false},{"title":"招惹","category":"\n                \n                                            暂无\n                                    \n                            ","url":"https://m.weibo.cn/search?containerid=100103type%3D1%26t%3D10%26q%3D%E6%8B%9B%E6%83%B9&stream_entry_id=31&isnewpage=1&extparam=seat%3D1%26flag%3D0%26stream_entry_id%3D31%26q%3D%25E6%258B%259B%25E6%2583%25B9%26filter_type%3Drealtimehot%26band_rank%3D46%26realpos%3D46%26c_type%3D31%26dgr%3D0%26pos%3D47%26cate%3D5001%26lcate%3D5001%26display_time%3D1680203044%26pre_seqid%3D1680203044773027221141&luicode=10000011&lfid=106003type%3D25%26t%3D3%26disable_hot%3D1%26filter_type%3Drealtimehot","hot":"剧集 22391","ads":false},{"title":"马嘉祺两首歌都入选最佳金曲","category":"综艺-内地综艺  ","description":"声生不息•宝岛季，天生歌者马嘉祺","url":"https://m.weibo.cn/search?containerid=100103type%3D1%26t%3D10%26q%3D%23%E9%A9%AC%E5%98%89%E7%A5%BA%E4%B8%A4%E9%A6%96%E6%AD%8C%E9%83%BD%E5%85%A5%E9%80%89%E6%9C%80%E4%BD%B3%E9%87%91%E6%9B%B2%23&stream_entry_id=31&isnewpage=1&extparam=seat%3D1%26flag%3D0%26stream_entry_id%3D31%26q%3D%2523%25E9%25A9%25AC%25E5%2598%2589%25E7%25A5%25BA%25E4%25B8%25A4%25E9%25A6%2596%25E6%25AD%258C%25E9%2583%25BD%25E5%2585%25A5%25E9%2580%2589%25E6%259C%2580%25E4%25BD%25B3%25E9%2587%2591%25E6%259B%25B2%2523%26filter_type%3Drealtimehot%26band_rank%3D47%26realpos%3D47%26c_type%3D31%26dgr%3D0%26pos%3D48%26cate%3D5001%26lcate%3D5001%26display_time%3D1680203044%26pre_seqid%3D1680203044773027221141&luicode=10000011&lfid=106003type%3D25%26t%3D3%26disable_hot%3D1%26filter_type%3Drealtimehot","hot":"综艺 22378","ads":false},{"title":"小义","category":"\n                \n                                            暂无\n                                    \n                            ","url":"https://m.weibo.cn/search?containerid=100103type%3D1%26t%3D10%26q%3D%E5%B0%8F%E4%B9%89&stream_entry_id=31&isnewpage=1&extparam=seat%3D1%26flag%3D0%26stream_entry_id%3D31%26q%3D%25E5%25B0%258F%25E4%25B9%2589%26filter_type%3Drealtimehot%26band_rank%3D48%26realpos%3D48%26c_type%3D31%26dgr%3D0%26pos%3D49%26cate%3D5001%26lcate%3D5001%26display_time%3D1680203044%26pre_seqid%3D1680203044773027221141&luicode=10000011&lfid=106003type%3D25%26t%3D3%26disable_hot%3D1%26filter_type%3Drealtimehot","hot":22366,"ads":false},{"title":"BoysPlanet三公竞演","category":"综艺-日韩综艺  ","description":"Mnet《Boys Planet》第三次公演竞演","url":"https://m.weibo.cn/search?containerid=100103type%3D1%26t%3D10%26q%3D%23BoysPlanet%E4%B8%89%E5%85%AC%E7%AB%9E%E6%BC%94%23&stream_entry_id=31&isnewpage=1&extparam=seat%3D1%26flag%3D0%26stream_entry_id%3D31%26q%3D%2523BoysPlanet%25E4%25B8%2589%25E5%2585%25AC%25E7%25AB%259E%25E6%25BC%2594%2523%26filter_type%3Drealtimehot%26band_rank%3D49%26realpos%3D49%26c_type%3D31%26dgr%3D0%26pos%3D50%26cate%3D5001%26lcate%3D5001%26display_time%3D1680203044%26pre_seqid%3D1680203044773027221141&luicode=10000011&lfid=106003type%3D25%26t%3D3%26disable_hot%3D1%26filter_type%3Drealtimehot","hot":"综艺 22359","ads":false},{"title":"宋涛在武汉会见马英九一行","category":"时事  ","url":"https://m.weibo.cn/search?containerid=100103type%3D1%26t%3D10%26q%3D%23%E5%AE%8B%E6%B6%9B%E5%9C%A8%E6%AD%A6%E6%B1%89%E4%BC%9A%E8%A7%81%E9%A9%AC%E8%8B%B1%E4%B9%9D%E4%B8%80%E8%A1%8C%23&stream_entry_id=31&isnewpage=1&extparam=seat%3D1%26flag%3D0%26stream_entry_id%3D31%26q%3D%2523%25E5%25AE%258B%25E6%25B6%259B%25E5%259C%25A8%25E6%25AD%25A6%25E6%25B1%2589%25E4%25BC%259A%25E8%25A7%2581%25E9%25A9%25AC%25E8%258B%25B1%25E4%25B9%259D%25E4%25B8%2580%25E8%25A1%258C%2523%26filter_type%3Drealtimehot%26band_rank%3D50%26realpos%3D50%26c_type%3D31%26dgr%3D0%26pos%3D51%26cate%3D5001%26lcate%3D5001%26display_time%3D1680203044%26pre_seqid%3D1680203044773027221141&luicode=10000011&lfid=106003type%3D25%26t%3D3%26disable_hot%3D1%26filter_type%3Drealtimehot","hot":22351,"ads":false},{"title":"天猫年度新品大奖揭幕","category":"社会  ","url":"https://m.weibo.cn/search?containerid=100103type%3D1%26t%3D10%26q%3D%23%E5%A4%A9%E7%8C%AB%E5%B9%B4%E5%BA%A6%E6%96%B0%E5%93%81%E5%A4%A7%E5%A5%96%E6%8F%AD%E5%B9%95%23&stream_entry_id=31&isnewpage=1&extparam=seat%3D1%26lcate%3D5001%26band_rank%3D4%26topic_ad%3D1%26q%3D%2523%25E5%25A4%25A9%25E7%258C%25AB%25E5%25B9%25B4%25E5%25BA%25A6%25E6%2596%25B0%25E5%2593%2581%25E5%25A4%25A7%25E5%25A5%2596%25E6%258F%25AD%25E5%25B9%2595%2523%26filter_type%3Drealtimehot%26stream_entry_id%3D31%26adid%3D184815%26c_type%3D31%26dgr%3D0%26pos%3D3%26cate%3D5001%26display_time%3D1680199473%26pre_seqid%3D1680199473323927167186&luicode=10000011&lfid=106003type%3D25%26t%3D3%26disable_hot%3D1%26filter_type%3Drealtimehot","hot":"","ads":true},{"title":"科学家是如何治理荒漠化的","category":"\n                \n                                            暂无\n                                    \n                            ","url":"https://m.weibo.cn/search?containerid=100103type%3D1%26t%3D10%26q%3D%E7%A7%91%E5%AD%A6%E5%AE%B6%E6%98%AF%E5%A6%82%E4%BD%95%E6%B2%BB%E7%90%86%E8%8D%92%E6%BC%A0%E5%8C%96%E7%9A%84&stream_entry_id=31&isnewpage=1&extparam=seat%3D1%26flag%3D0%26lcate%3D5001%26band_rank%3D39%26q%3D%25E7%25A7%2591%25E5%25AD%25A6%25E5%25AE%25B6%25E6%2598%25AF%25E5%25A6%2582%25E4%25BD%2595%25E6%25B2%25BB%25E7%2590%2586%25E8%258D%2592%25E6%25BC%25A0%25E5%258C%2596%25E7%259A%2584%26filter_type%3Drealtimehot%26stream_entry_id%3D31%26c_type%3D31%26dgr%3D0%26pos%3D39%26cate%3D5001%26realpos%3D39%26display_time%3D1680199473%26pre_seqid%3D1680199473323927167186&luicode=10000011&lfid=106003type%3D25%26t%3D3%26disable_hot%3D1%26filter_type%3Drealtimehot","hot":36465,"ads":false},{"title":"声生不息宝岛季下期有于文文","category":"综艺  ","description":"#声生不息宝岛季下期预告#中惊现@Kelly于文文 ！","url":"https://m.weibo.cn/search?containerid=100103type%3D1%26t%3D10%26q%3D%23%E5%A3%B0%E7%94%9F%E4%B8%8D%E6%81%AF%E5%AE%9D%E5%B2%9B%E5%AD%A3%E4%B8%8B%E6%9C%9F%E6%9C%89%E4%BA%8E%E6%96%87%E6%96%87%23&stream_entry_id=31&isnewpage=1&extparam=seat%3D1%26flag%3D0%26lcate%3D5001%26band_rank%3D40%26q%3D%2523%25E5%25A3%25B0%25E7%2594%259F%25E4%25B8%258D%25E6%2581%25AF%25E5%25AE%259D%25E5%25B2%259B%25E5%25AD%25A3%25E4%25B8%258B%25E6%259C%259F%25E6%259C%2589%25E4%25BA%258E%25E6%2596%2587%25E6%2596%2587%2523%26filter_type%3Drealtimehot%26stream_entry_id%3D31%26c_type%3D31%26dgr%3D0%26pos%3D40%26cate%3D5001%26realpos%3D40%26display_time%3D1680199473%26pre_seqid%3D1680199473323927167186&luicode=10000011&lfid=106003type%3D25%26t%3D3%26disable_hot%3D1%26filter_type%3Drealtimehot","hot":"综艺 35783","ads":false},{"title":"有能力有条件的民营企业要加强自主创新","category":"时事  ","description":"有能力、有条件的民营企业要加强自主创新，在推进科技自立自强和科技成果转化中发挥更大作用。","url":"https://m.weibo.cn/search?containerid=100103type%3D1%26t%3D10%26q%3D%23%E6%9C%89%E8%83%BD%E5%8A%9B%E6%9C%89%E6%9D%A1%E4%BB%B6%E7%9A%84%E6%B0%91%E8%90%A5%E4%BC%81%E4%B8%9A%E8%A6%81%E5%8A%A0%E5%BC%BA%E8%87%AA%E4%B8%BB%E5%88%9B%E6%96%B0%23&stream_entry_id=51&isnewpage=1&extparam=seat%3D1%26c_type%3D51%26dgr%3D0%26pos%3D0%26filter_type%3Drealtimehot%26stream_entry_id%3D51%26cate%3D10103%26display_time%3D1680195844%26pre_seqid%3D168019584489293087252&luicode=10000011&lfid=106003type%3D25%26t%3D3%26disable_hot%3D1%26filter_type%3Drealtimehot","ads":false},{"title":"益禾堂螺蛳粉是什么梗","category":"美食  ","url":"https://m.weibo.cn/search?containerid=100103type%3D1%26t%3D10%26q%3D%23%E7%9B%8A%E7%A6%BE%E5%A0%82%E8%9E%BA%E8%9B%B3%E7%B2%89%E6%98%AF%E4%BB%80%E4%B9%88%E6%A2%97%23&stream_entry_id=31&isnewpage=1&extparam=seat%3D1%26lcate%3D5001%26topic_ad%3D1%26filter_type%3Drealtimehot%26c_type%3D31%26q%3D%2523%25E7%259B%258A%25E7%25A6%25BE%25E5%25A0%2582%25E8%259E%25BA%25E8%259B%25B3%25E7%25B2%2589%25E6%2598%25AF%25E4%25BB%2580%25E4%25B9%2588%25E6%25A2%2597%2523%26dgr%3D0%26pos%3D3%26band_rank%3D4%26cate%3D5001%26stream_entry_id%3D31%26adid%3D184811%26display_time%3D1680195844%26pre_seqid%3D168019584489293087252&luicode=10000011&lfid=106003type%3D25%26t%3D3%26disable_hot%3D1%26filter_type%3Drealtimehot","hot":"","ads":true},{"title":"一只小狗感动全球数亿人","category":"其他  ","description":"电影《忠犬八公》今日全国上映，感动全球数亿人的小狗终于来和大家见面啦～","url":"https://m.weibo.cn/search?containerid=100103type%3D1%26t%3D10%26q%3D%23%E4%B8%80%E5%8F%AA%E5%B0%8F%E7%8B%97%E6%84%9F%E5%8A%A8%E5%85%A8%E7%90%83%E6%95%B0%E4%BA%BF%E4%BA%BA%23&stream_entry_id=31&isnewpage=1&extparam=seat%3D1%26lcate%3D5001%26topic_ad%3D1%26filter_type%3Drealtimehot%26c_type%3D31%26q%3D%2523%25E4%25B8%2580%25E5%258F%25AA%25E5%25B0%258F%25E7%258B%2597%25E6%2584%259F%25E5%258A%25A8%25E5%2585%25A8%25E7%2590%2583%25E6%2595%25B0%25E4%25BA%25BF%25E4%25BA%25BA%2523%26dgr%3D0%26pos%3D7%26band_rank%3D7%26cate%3D5001%26stream_entry_id%3D31%26adid%3D184784%26display_time%3D1680195844%26pre_seqid%3D168019584489293087252&luicode=10000011&lfid=106003type%3D25%26t%3D3%26disable_hot%3D1%26filter_type%3Drealtimehot","hot":"","ads":true},{"title":"五月天永远陪我们20岁","category":"综艺  ","description":"《声生不息》短片：“听五月天的人好像永远都不会长大一样”“听五月天的时候，你要永远记得，五月天永远陪你二十岁”","url":"https://m.weibo.cn/search?containerid=100103type%3D1%26t%3D10%26q%3D%23%E4%BA%94%E6%9C%88%E5%A4%A9%E6%B0%B8%E8%BF%9C%E9%99%AA%E6%88%91%E4%BB%AC20%E5%B2%81%23&stream_entry_id=31&isnewpage=1&extparam=seat%3D1%26filter_type%3Drealtimehot%26stream_entry_id%3D31%26realpos%3D44%26c_type%3D31%26q%3D%2523%25E4%25BA%2594%25E6%259C%2588%25E5%25A4%25A9%25E6%25B0%25B8%25E8%25BF%259C%25E9%2599%25AA%25E6%2588%2591%25E4%25BB%25AC20%25E5%25B2%2581%2523%26dgr%3D0%26pos%3D45%26cate%3D5001%26lcate%3D5001%26band_rank%3D44%26flag%3D0%26display_time%3D1680195844%26pre_seqid%3D168019584489293087252&luicode=10000011&lfid=106003type%3D25%26t%3D3%26disable_hot%3D1%26filter_type%3Drealtimehot","hot":"综艺 61127","ads":false},{"title":"王楚钦男单夺冠","category":"体育  ","description":"“直通德班”2023国乒世乒赛选拔赛第二站，王楚钦获男单决赛冠军。","url":"https://m.weibo.cn/search?containerid=100103type%3D1%26t%3D10%26q%3D%23%E7%8E%8B%E6%A5%9A%E9%92%A6%E7%94%B7%E5%8D%95%E5%A4%BA%E5%86%A0%23&stream_entry_id=31&isnewpage=1&extparam=seat%3D1%26filter_type%3Drealtimehot%26stream_entry_id%3D31%26realpos%3D47%26c_type%3D31%26q%3D%2523%25E7%258E%258B%25E6%25A5%259A%25E9%2592%25A6%25E7%2594%25B7%25E5%258D%2595%25E5%25A4%25BA%25E5%2586%25A0%2523%26dgr%3D0%26pos%3D48%26cate%3D5001%26lcate%3D5001%26band_rank%3D47%26flag%3D0%26display_time%3D1680195844%26pre_seqid%3D168019584489293087252&luicode=10000011&lfid=106003type%3D25%26t%3D3%26disable_hot%3D1%26filter_type%3Drealtimehot","hot":55202,"ads":false},{"title":"AI","category":"\n                \n                                            暂无\n                                    \n                            ","url":"https://m.weibo.cn/search?containerid=100103type%3D1%26t%3D10%26q%3DAI&stream_entry_id=31&isnewpage=1&extparam=seat%3D1%26filter_type%3Drealtimehot%26stream_entry_id%3D31%26realpos%3D49%26c_type%3D31%26q%3DAI%26dgr%3D0%26pos%3D50%26cate%3D5001%26lcate%3D5001%26band_rank%3D49%26flag%3D0%26display_time%3D1680195844%26pre_seqid%3D168019584489293087252&luicode=10000011&lfid=106003type%3D25%26t%3D3%26disable_hot%3D1%26filter_type%3Drealtimehot","hot":54323,"ads":false},{"title":"被张凌赫甜到心芭","category":"明星  ","url":"https://m.weibo.cn/search?containerid=100103type%3D1%26t%3D10%26q%3D%23%E8%A2%AB%E5%BC%A0%E5%87%8C%E8%B5%AB%E7%94%9C%E5%88%B0%E5%BF%83%E8%8A%AD%23&stream_entry_id=31&isnewpage=1&extparam=seat%3D1%26topic_ad%3D1%26lcate%3D5001%26stream_entry_id%3D31%26filter_type%3Drealtimehot%26c_type%3D31%26adid%3D184647%26cate%3D5001%26dgr%3D0%26pos%3D3%26q%3D%2523%25E8%25A2%25AB%25E5%25BC%25A0%25E5%2587%258C%25E8%25B5%25AB%25E7%2594%259C%25E5%2588%25B0%25E5%25BF%2583%25E8%258A%25AD%2523%26band_rank%3D4%26display_time%3D1680192261%26pre_seqid%3D1680192261411025650434&luicode=10000011&lfid=106003type%3D25%26t%3D3%26disable_hot%3D1%26filter_type%3Drealtimehot","hot":"","ads":true},{"title":"尤长靖EP肆无忌惮的恋人","category":"音乐  ","description":"尤长靖EP《肆无忌惮的恋人》歌词海报释出。有关于「恋爱」的情歌，一起期待3月31日00:00音源上线 ，听听音乐里爱的浪漫！","url":"https://m.weibo.cn/search?containerid=100103type%3D1%26t%3D10%26q%3D%23%E5%B0%A4%E9%95%BF%E9%9D%96EP%E8%82%86%E6%97%A0%E5%BF%8C%E6%83%AE%E7%9A%84%E6%81%8B%E4%BA%BA%23&stream_entry_id=31&isnewpage=1&extparam=seat%3D1%26lcate%3D5001%26stream_entry_id%3D31%26filter_type%3Drealtimehot%26c_type%3D31%26adid%3D184819%26cate%3D5001%26dgr%3D0%26pos%3D7%26q%3D%2523%25E5%25B0%25A4%25E9%2595%25BF%25E9%259D%2596EP%25E8%2582%2586%25E6%2597%25A0%25E5%25BF%258C%25E6%2583%25AE%25E7%259A%2584%25E6%2581%258B%25E4%25BA%25BA%2523%26band_rank%3D7%26display_time%3D1680192261%26pre_seqid%3D1680192261411025650434&luicode=10000011&lfid=106003type%3D25%26t%3D3%26disable_hot%3D1%26filter_type%3Drealtimehot","hot":"","ads":true},{"title":"赵丽颖剪短发了","category":"明星  ","description":"好久不见的“赵丽隐”出现啦！短发是甜甜妹宝~","url":"https://m.weibo.cn/search?containerid=100103type%3D1%26t%3D10%26q%3D%23%E8%B5%B5%E4%B8%BD%E9%A2%96%E5%89%AA%E7%9F%AD%E5%8F%91%E4%BA%86%23&stream_entry_id=31&isnewpage=1&extparam=seat%3D1%26lcate%3D5001%26stream_entry_id%3D31%26filter_type%3Drealtimehot%26c_type%3D31%26realpos%3D11%26cate%3D5001%26dgr%3D0%26pos%3D12%26q%3D%2523%25E8%25B5%25B5%25E4%25B8%25BD%25E9%25A2%2596%25E5%2589%25AA%25E7%259F%25AD%25E5%258F%2591%25E4%25BA%2586%2523%26band_rank%3D11%26flag%3D2%26display_time%3D1680192261%26pre_seqid%3D1680192261411025650434&luicode=10000011&lfid=106003type%3D25%26t%3D3%26disable_hot%3D1%26filter_type%3Drealtimehot","hot":317125,"ads":false},{"title":"肖战张艺兴王源陈伟霆MV视频","category":"明星  ","description":"肖战张艺兴王源陈伟霆MV视频，一起来看看吧","url":"https://m.weibo.cn/search?containerid=100103type%3D1%26t%3D10%26q%3D%23%E8%82%96%E6%88%98%E5%BC%A0%E8%89%BA%E5%85%B4%E7%8E%8B%E6%BA%90%E9%99%88%E4%BC%9F%E9%9C%86MV%E8%A7%86%E9%A2%91%23&stream_entry_id=31&isnewpage=1&extparam=seat%3D1%26lcate%3D5001%26stream_entry_id%3D31%26filter_type%3Drealtimehot%26c_type%3D31%26realpos%3D42%26cate%3D5001%26dgr%3D0%26pos%3D43%26q%3D%2523%25E8%2582%2596%25E6%2588%2598%25E5%25BC%25A0%25E8%2589%25BA%25E5%2585%25B4%25E7%258E%258B%25E6%25BA%2590%25E9%2599%2588%25E4%25BC%259F%25E9%259C%2586MV%25E8%25A7%2586%25E9%25A2%2591%2523%26band_rank%3D42%26flag%3D0%26display_time%3D1680192261%26pre_seqid%3D1680192261411025650434&luicode=10000011&lfid=106003type%3D25%26t%3D3%26disable_hot%3D1%26filter_type%3Drealtimehot","hot":"音乐 216473","ads":false},{"title":"那英坏特Melody","category":"综艺  ","description":"《声生不息》一公下半场舞台，那英坏特Melody","url":"https://m.weibo.cn/search?containerid=100103type%3D1%26t%3D10%26q%3D%23%E9%82%A3%E8%8B%B1%E5%9D%8F%E7%89%B9Melody%23&stream_entry_id=31&isnewpage=1&extparam=seat%3D1%26lcate%3D5001%26stream_entry_id%3D31%26filter_type%3Drealtimehot%26c_type%3D31%26realpos%3D46%26cate%3D5001%26dgr%3D0%26pos%3D47%26q%3D%2523%25E9%2582%25A3%25E8%258B%25B1%25E5%259D%258F%25E7%2589%25B9Melody%2523%26band_rank%3D46%26flag%3D1%26display_time%3D1680192261%26pre_seqid%3D1680192261411025650434&luicode=10000011&lfid=106003type%3D25%26t%3D3%26disable_hot%3D1%26filter_type%3Drealtimehot","hot":"综艺 216451","ads":false}]